vcflib/__init__.py
vcflib/bgzf.py
vcflib/compat.py
vcflib/sharder.py
vcflib/tabix.py
vcflib/tribble.py
vcflib/vcf.py
vcflib-1.0.0.dist-info/LICENSE
vcflib-1.0.0.dist-info/METADATA
vcflib-1.0.0.dist-info/WHEEL
vcflib-1.0.0.dist-info/RECORD
