Metadata-Version: 2.3
Name: vcflib
Version: 1.0.0
Summary: An open-source Python library for VCF parsing and manipulation
Author: Sentieon
Author-email: support@sentieon.com
Requires-Python: >=2.7, !=3.0.*, !=3.1.*, !=3.2.*, !=3.3.*, !=3.4.*, !=3.5.*, >=3.6
Classifier: Development Status :: 5 - Production/Stable
Classifier: License :: OSI Approved :: BSD License
Classifier: Programming Language :: Python :: 3
Classifier: Programming Language :: Python :: 2.7
Project-URL: Homepage, https://github.com/Sentieon/vcflib
Project-URL: Source, https://github.com/Sentieon/vcflib
